{
  "Name": "1С:Управление лизинговой компанией. Расширение для 1С:ERP",
  "Category": {
    "ID": 162,
    "Name": "Отраслевые решения"
  },
  "ReleasesCount": 5,
  "ReleasesHistory": [
    {
      "Created": "2020-01-10T19:32:36",
      "Name": "1С:Управление лизинговой компанией. Расширение для 1С:ERP",
      "Version": "",
      "PublishingDate": "0001-01-01T00:00:00",
      "PlanVersions": [],
      "PlanReleaseDates": [],
      "PlanUpdateDates": [],
      "DemoVersions": [],
      "DemoPublicationDates": []
    },
    {
      "Created": "2020-05-13T15:14:06",
      "Name": "1С:Управление лизинговой компанией. Расширение для 1С:ERP",
      "Version": "",
      "PublishingDate": "0001-01-01T00:00:00",
      "PlanVersions": [
        "1.0.1.2"
      ],
      "PlanReleaseDates": [
        "2020-05-19T00:00:00"
      ],
      "PlanUpdateDates": [
        "2020-05-13T00:00:00"
      ],
      "DemoVersions": [],
      "DemoPublicationDates": []
    },
    {
      "Created": "2020-05-19T11:44:04",
      "Name": "1С:Управление лизинговой компанией. Расширение для 1С:ERP",
      "Version": "",
      "PublishingDate": "0001-01-01T00:00:00",
      "PlanVersions": [
        "1.0.1.2"
      ],
      "PlanReleaseDates": [
        "2020-05-21T00:00:00"
      ],
      "PlanUpdateDates": [
        "2020-05-19T00:00:00"
      ],
      "DemoVersions": [],
      "DemoPublicationDates": []
    },
    {
      "Created": "2020-05-22T10:44:05",
      "Name": "1С:Управление лизинговой компанией. Расширение для 1С:ERP",
      "Version": "",
      "PublishingDate": "0001-01-01T00:00:00",
      "PlanVersions": [
        "1.0.1.2"
      ],
      "PlanReleaseDates": [
        "2020-05-26T00:00:00"
      ],
      "PlanUpdateDates": [
        "2020-05-22T00:00:00"
      ],
      "DemoVersions": [],
      "DemoPublicationDates": []
    },
    {
      "Created": "2020-05-25T19:44:05",
      "Name": "1С:Управление лизинговой компанией. Расширение для 1С:ERP",
      "Version": "",
      "PublishingDate": "0001-01-01T00:00:00",
      "PlanVersions": [
        "1.0.1.2"
      ],
      "PlanReleaseDates": [
        "2020-05-27T00:00:00"
      ],
      "PlanUpdateDates": [
        "2020-05-25T00:00:00"
      ],
      "DemoVersions": [],
      "DemoPublicationDates": []
    }
  ]
}