{
  "Name": "Бухгалтерия для Таджикистана",
  "Category": {
    "ID": 912,
    "Name": "Типовые конфигурации фирмы \"1С\" для Таджикистана"
  },
  "ReleasesCount": 7,
  "ReleasesHistory": [
    {
      "Created": "2018-12-13T00:05:43",
      "Name": "Бухгалтерия для Таджикистана",
      "Version": "3.0.10.5",
      "PublishingDate": "2018-11-21T00:00:00",
      "PlanVersions": [],
      "PlanReleaseDates": [],
      "PlanUpdateDates": [],
      "DemoVersions": [],
      "DemoPublicationDates": []
    },
    {
      "Created": "2019-05-13T16:54:51",
      "Name": "Бухгалтерия для Таджикистана",
      "Version": "3.0.11.8",
      "PublishingDate": "2019-05-13T00:00:00",
      "PlanVersions": [],
      "PlanReleaseDates": [],
      "PlanUpdateDates": [],
      "DemoVersions": [],
      "DemoPublicationDates": []
    },
    {
      "Created": "2019-09-20T14:32:24",
      "Name": "Бухгалтерия для Таджикистана",
      "Version": "3.0.11.8",
      "PublishingDate": "2019-05-13T00:00:00",
      "PlanVersions": [
        "3.0.12"
      ],
      "PlanReleaseDates": [
        "2019-10-04T00:00:00"
      ],
      "PlanUpdateDates": [
        "2019-09-20T00:00:00"
      ],
      "DemoVersions": [],
      "DemoPublicationDates": []
    },
    {
      "Created": "2019-10-09T16:32:21",
      "Name": "Бухгалтерия для Таджикистана",
      "Version": "3.0.12.24",
      "PublishingDate": "2019-10-09T00:00:00",
      "PlanVersions": [],
      "PlanReleaseDates": [],
      "PlanUpdateDates": [],
      "DemoVersions": [],
      "DemoPublicationDates": []
    },
    {
      "Created": "2020-07-01T10:00:12",
      "Name": "Бухгалтерия для Таджикистана",
      "Version": "3.0.12.24",
      "PublishingDate": "2019-10-09T00:00:00",
      "PlanVersions": [
        "3.0.13"
      ],
      "PlanReleaseDates": [
        "2020-07-10T00:00:00"
      ],
      "PlanUpdateDates": [
        "2020-07-01T00:00:00"
      ],
      "DemoVersions": [],
      "DemoPublicationDates": []
    },
    {
      "Created": "2020-07-07T23:30:10",
      "Name": "Бухгалтерия для Таджикистана",
      "Version": "3.0.13.7",
      "PublishingDate": "2020-07-07T00:00:00",
      "PlanVersions": [],
      "PlanReleaseDates": [],
      "PlanUpdateDates": [],
      "DemoVersions": [],
      "DemoPublicationDates": []
    },
    {
      "Created": "2020-11-26T17:00:12",
      "Name": "Бухгалтерия для Таджикистана",
      "Version": "3.0.13.7",
      "PublishingDate": "2020-07-07T00:00:00",
      "PlanVersions": [
        "3.0.14"
      ],
      "PlanReleaseDates": [
        "2020-12-07T00:00:00"
      ],
      "PlanUpdateDates": [
        "2020-11-26T00:00:00"
      ],
      "DemoVersions": [],
      "DemoPublicationDates": []
    }
  ]
}